llm/__init__.py
llm/billing.py
llm/constructor.py
llm/counter.py
llm/direction.py
llm/model_registry.py
llm/moderations.py
llm/service.py
llm/test_connections.py
llm/token_counters.py
llm/usage.py
llm/cbr/__init__.py
llm/cbr/cbr.py
llm/prepare_chat/__init__.py
llm/prepare_chat/prepare_chat.py
llm/providers/__init__.py
llm/providers/_base.py
llm/providers/_factory.py
llm/providers/anthropic.py
llm/providers/cerebras.py
llm/providers/deepseek.py
llm/providers/gigachat.py
llm/providers/google.py
llm/providers/openai.py
llm/providers/openrouter.py
llm/providers/xai.py
llm/pydantic_utils/__init__.py
llm/pydantic_utils/checker.py
llm/tokenizer/__init__.py
llm/tokenizer/deepseek/__init__.py
llm/tokenizer/deepseek/deepseek.py
llm/types/__init__.py
llm/types/types.py
llm/tokenizer/deepseek/tokenizer.json
universal_llm_service-1.0.26.dist-info/METADATA
universal_llm_service-1.0.26.dist-info/WHEEL
universal_llm_service-1.0.26.dist-info/licenses/LICENSE
universal_llm_service-1.0.26.dist-info/RECORD
