Metadata-Version: 2.4
Name: universal-llm-service
Version: 1.0.26
Summary: Библиотека для работы с языковыми моделями
Project-URL: Homepage, https://github.com/DenisShahbazyan/LLM_Service
Project-URL: Bug Tracker, https://github.com/DenisShahbazyan/LLM_Service/issues
Author-email: Денис Шахбазян <otbephncb@gmail.com>
License-File: LICENSE
Classifier: Development Status :: 4 - Beta
Classifier: License :: OSI Approved :: MIT License
Classifier: Programming Language :: Python :: 3.11
Classifier: Programming Language :: Python :: 3.12
Classifier: Programming Language :: Python :: 3.13
Requires-Python: >=3.11
Requires-Dist: aiohttp>=3.12.14
Requires-Dist: langchain>=0.3.26
Provides-Extra: all
Requires-Dist: langchain-anthropic>=0.3.19; extra == 'all'
Requires-Dist: langchain-cerebras>=0.5.0; extra == 'all'
Requires-Dist: langchain-deepseek>=0.1.4; extra == 'all'
Requires-Dist: langchain-gigachat>=0.3.12; extra == 'all'
Requires-Dist: langchain-google-genai>=2.1.10; extra == 'all'
Requires-Dist: langchain-openai>=0.3.32; extra == 'all'
Requires-Dist: langchain-xai>=0.2.5; extra == 'all'
Requires-Dist: tiktoken>=0.11.0; extra == 'all'
Requires-Dist: tokenizers>=0.22.0; extra == 'all'
Provides-Extra: anthropic
Requires-Dist: langchain-anthropic>=0.3.19; extra == 'anthropic'
Provides-Extra: cerebras
Requires-Dist: langchain-cerebras>=0.5.0; extra == 'cerebras'
Provides-Extra: deepseek
Requires-Dist: langchain-deepseek>=0.1.4; extra == 'deepseek'
Requires-Dist: tokenizers>=0.22.0; extra == 'deepseek'
Provides-Extra: gemini
Requires-Dist: langchain-google-genai>=2.1.10; extra == 'gemini'
Provides-Extra: gigachat
Requires-Dist: langchain-gigachat>=0.3.12; extra == 'gigachat'
Provides-Extra: openai
Requires-Dist: langchain-openai>=0.3.32; extra == 'openai'
Requires-Dist: tiktoken>=0.11.0; extra == 'openai'
Provides-Extra: openrouter
Requires-Dist: langchain-openai>=0.3.32; extra == 'openrouter'
Requires-Dist: tiktoken>=0.11.0; extra == 'openrouter'
Provides-Extra: xai
Requires-Dist: langchain-xai>=0.2.5; extra == 'xai'
